daiedge_vlab/__init__.py
daiedge_vlab/api.py
daiedge_vlab/config.py
daiedge_vlab-0.2.11.dist-info/licenses/LICENSE
daiedge_vlab-0.2.11.dist-info/METADATA
daiedge_vlab-0.2.11.dist-info/WHEEL
daiedge_vlab-0.2.11.dist-info/top_level.txt
daiedge_vlab-0.2.11.dist-info/RECORD
