Metadata-Version: 2.4
Name: daiedge-vlab
Version: 0.2.11
Summary: Python client for dAIEdge VLab: simplifies interaction with the API and provides utilities for model benchmarking and on-device training.
Author-email: Baptiste Dupertuis <baptiste.dupertuis@he-arc.ch>
License: MIT
Project-URL: Homepage, https://gitlab.com/daiedge/poc_virtuallab/daiedge-vlab
Project-URL: Source, https://gitlab.com/daiedge/poc_virtuallab/daiedge-vlab
Project-URL: Issues, https://gitlab.com/daiedge/poc_virtuallab/daiedge-vlab/-/issues
Project-URL: Documentation, http://public-virtuallab-docs-tica-23tica04-daiedge-poc-6eb4f1c0e44fb2.pages-rad.ing.he-arc.ch/user/api/
Requires-Python: >=3.7
License-File: LICENSE
Requires-Dist: requests>=2.20
Requires-Dist: PyYAML>=6.0
Provides-Extra: dev
Requires-Dist: pytest; extra == "dev"
Requires-Dist: ruff; extra == "dev"
Requires-Dist: build; extra == "dev"
Requires-Dist: twine; extra == "dev"
Dynamic: license-file
